<country>
<name>Belgium</name>
<area>
<vertex lat="51.432830" lon="4.816068"/>
<vertex lat="51.412056" lon="4.820667"/>
<vertex lat="51.403271" lon="4.848056"/>
<vertex lat="51.407767" lon="4.943916"/>
<vertex lat="51.445361" lon="4.992595"/>
<vertex lat="51.469107" lon="5.030939"/>
<vertex lat="51.453139" lon="5.059464"/>
<vertex lat="51.406811" lon="5.073417"/>
<vertex lat="51.346479" lon="5.099875"/>
<vertex lat="51.278963" lon="5.214183"/>
<vertex lat="51.259714" lon="5.310870"/>
<vertex lat="51.272995" lon="5.429777"/>
<vertex lat="51.285035" lon="5.476855"/>
<vertex lat="51.275010" lon="5.508739"/>
<vertex lat="51.239302" lon="5.540417"/>
<vertex lat="51.198451" lon="5.608785"/>
<vertex lat="51.169487" lon="5.752393"/>
<vertex lat="51.153054" lon="5.796473"/>
<vertex lat="51.125639" lon="5.827118"/>
<vertex lat="51.086417" lon="5.818281"/>
<vertex lat="50.988748" lon="5.749758"/>
<vertex lat="50.959913" lon="5.740818"/>
<vertex lat="50.950224" lon="5.749965"/>
<vertex lat="50.932137" lon="5.736632"/>
<vertex lat="50.866663" lon="5.647542"/>
<vertex lat="50.843615" lon="5.639480"/>
<vertex lat="50.805943" lon="5.669091"/>
<vertex lat="50.774742" lon="5.693587"/>
<vertex lat="50.781035" lon="5.694568"/>
<vertex lat="50.809147" lon="5.830993"/>
<vertex lat="50.752561" lon="5.892488"/>
<vertex lat="50.754525" lon="5.797404"/>
<vertex lat="50.750443" lon="5.993929"/>
<vertex lat="50.732227" lon="6.005970"/>
<vertex lat="50.679232" lon="6.119451"/>
<vertex lat="50.637271" lon="6.154488"/>
<vertex lat="50.596705" lon="6.235981"/>
<vertex lat="50.545339" lon="6.168440"/>
<vertex lat="50.522498" lon="6.178672"/>
<vertex lat="50.499114" lon="6.203064"/>
<vertex lat="50.485498" lon="6.294944"/>
<vertex lat="50.451753" lon="6.340936"/>
<vertex lat="50.400257" lon="6.343623"/>
<vertex lat="50.316154" lon="6.364501"/>
<vertex lat="50.232645" lon="6.175055"/>
<vertex lat="50.139369" lon="6.121311"/>
<vertex lat="50.120972" lon="6.116506"/>
<vertex lat="50.123763" lon="6.110046"/>
<vertex lat="50.154588" lon="6.089065"/>
<vertex lat="50.154303" lon="6.054752"/>
<vertex lat="50.167171" lon="5.976307"/>
<vertex lat="50.082835" lon="5.866908"/>
<vertex lat="50.012684" lon="5.817402"/>
<vertex lat="49.961240" lon="5.788102"/>
<vertex lat="49.919641" lon="5.744074"/>
<vertex lat="49.875638" lon="5.735289"/>
<vertex lat="49.857164" lon="5.740766"/>
<vertex lat="49.833341" lon="5.725780"/>
<vertex lat="49.808278" lon="5.724953"/>
<vertex lat="49.758875" lon="5.787998"/>
<vertex lat="49.732159" lon="5.803708"/>
<vertex lat="49.644774" lon="5.880396"/>
<vertex lat="49.612838" lon="5.856573"/>
<vertex lat="49.578344" lon="5.837608"/>
<vertex lat="49.553823" lon="5.815439"/>
<vertex lat="49.538269" lon="5.789704"/>
<vertex lat="49.539199" lon="5.710484"/>
<vertex lat="49.528243" lon="5.610077"/>
<vertex lat="49.511035" lon="5.542432"/>
<vertex lat="49.510880" lon="5.507292"/>
<vertex lat="49.554469" lon="5.434635"/>
<vertex lat="49.619840" lon="5.353503"/>
<vertex lat="49.651001" lon="5.301982"/>
<vertex lat="49.677924" lon="5.278779"/>
<vertex lat="49.689241" lon="5.215010"/>
<vertex lat="49.721461" lon="5.124111"/>
<vertex lat="49.756550" lon="5.061066"/>
<vertex lat="49.778357" lon="5.006909"/>
<vertex lat="49.789261" lon="4.930583"/>
<vertex lat="49.788124" lon="4.867590"/>
<vertex lat="49.847139" lon="4.849141"/>
<vertex lat="49.914499" lon="4.841545"/>
<vertex lat="49.959586" lon="4.790023"/>
<vertex lat="50.135906" lon="4.860562"/>
<vertex lat="50.153192" lon="4.818652"/>
<vertex lat="50.139059" lon="4.772867"/>
<vertex lat="50.097046" lon="4.706617"/>
<vertex lat="50.046894" lon="4.675095"/>
<vertex lat="50.002452" lon="4.656181"/>
<vertex lat="49.960258" lon="4.545025"/>
<vertex lat="49.944962" lon="4.368705"/>
<vertex lat="49.960258" lon="4.176056"/>
<vertex lat="49.971575" lon="4.149339"/>
<vertex lat="49.984469" lon="4.137040"/>
<vertex lat="49.999997" lon="4.136833"/>
<vertex lat="50.023872" lon="4.150321"/>
<vertex lat="50.052811" lon="4.183859"/>
<vertex lat="50.094152" lon="4.192179"/>
<vertex lat="50.129886" lon="4.157710"/>
<vertex lat="50.143813" lon="4.135283"/>
<vertex lat="50.178410" lon="4.144120"/>
<vertex lat="50.221767" lon="4.169596"/>
<vertex lat="50.246494" lon="4.174557"/>
<vertex lat="50.321347" lon="4.044126"/>
<vertex lat="50.335946" lon="3.949713"/>
<vertex lat="50.338556" lon="3.858090"/>
<vertex lat="50.346953" lon="3.788586"/>
<vertex lat="50.343491" lon="3.748020"/>
<vertex lat="50.321657" lon="3.718874"/>
<vertex lat="50.306077" lon="3.689315"/>
<vertex lat="50.324784" lon="3.667301"/>
<vertex lat="50.457334" lon="3.626787"/>
<vertex lat="50.477359" lon="3.595367"/>
<vertex lat="50.499450" lon="3.476925"/>
<vertex lat="50.507357" lon="3.316211"/>
<vertex lat="50.531541" lon="3.273320"/>
<vertex lat="50.591176" lon="3.249755"/>
<vertex lat="50.662954" lon="3.234976"/>
<vertex lat="50.731684" lon="3.182008"/>
<vertex lat="50.748944" lon="3.154878"/>
<vertex lat="50.779433" lon="3.106870"/>
<vertex lat="50.766876" lon="3.022896"/>
<vertex lat="50.727033" lon="2.921972"/>
<vertex lat="50.716000" lon="2.862441"/>
<vertex lat="50.711789" lon="2.839755"/>
<vertex lat="50.750649" lon="2.759398"/>
<vertex lat="50.811421" lon="2.669119"/>
<vertex lat="50.875913" lon="2.596772"/>
<vertex lat="50.911776" lon="2.579254"/>
<vertex lat="50.955288" lon="2.601423"/>
<vertex lat="50.988568" lon="2.574810"/>
<vertex lat="51.049494" lon="2.536052"/>
<vertex lat="51.097140" lon="2.524942"/>
<vertex lat="51.265450" lon="2.960161"/>
<vertex lat="51.351595" lon="3.225158"/>
<vertex lat="51.377691" lon="3.350111"/>
<vertex lat="51.291133" lon="3.380083"/>
<vertex lat="51.263641" lon="3.402821"/>
<vertex lat="51.245761" lon="3.432483"/>
<vertex lat="51.242247" lon="3.471964"/>
<vertex lat="51.263641" lon="3.517129"/>
<vertex lat="51.286172" lon="3.580278"/>
<vertex lat="51.275682" lon="3.681822"/>
<vertex lat="51.254856" lon="3.755668"/>
<vertex lat="51.233204" lon="3.781919"/>
<vertex lat="51.212585" lon="3.830754"/>
<vertex lat="51.207676" lon="3.902067"/>
<vertex lat="51.247079" lon="4.039991"/>
<vertex lat="51.307101" lon="4.172593"/>
<vertex lat="51.348752" lon="4.211454"/>
<vertex lat="51.386476" lon="4.226130"/>
<vertex lat="51.361516" lon="4.304471"/>
<vertex lat="51.355987" lon="4.373718"/>
<vertex lat="51.367097" lon="4.404000"/>
<vertex lat="51.427611" lon="4.384777"/>
<vertex lat="51.459805" lon="4.440897"/>
<vertex lat="51.474688" lon="4.503426"/>
<vertex lat="51.448591" lon="4.531693"/>
<vertex lat="51.421926" lon="4.588795"/>
<vertex lat="51.421719" lon="4.633960"/>
<vertex lat="51.491095" lon="4.755658"/>
<vertex lat="51.477375" lon="4.784184"/>
<vertex lat="51.452725" lon="4.810590"/>
<vertex lat="51.432830" lon="4.816068"/>
</area>
</country>
